.bumpversion.cfg
.cookiecutterrc
.coveragerc
.editorconfig
.travis.yml
AUTHORS.rst
CHANGELOG.rst
CONTRIBUTING.rst
LICENSE
MANIFEST.in
README.rst
appveyor.yml
setup.cfg
setup.py
tox.ini
ci/appveyor-bootstrap.py
ci/appveyor-download.py
ci/appveyor-with-compiler.cmd
ci/bootstrap.py
ci/templates/.travis.yml
ci/templates/appveyor.yml
ci/templates/tox.ini
docs/authors.rst
docs/changelog.rst
docs/conf.py
docs/contributing.rst
docs/index.rst
docs/installation.rst
docs/readme.rst
docs/requirements.txt
docs/spelling_wordlist.txt
docs/usage.rst
docs/reference/conditions.rst
docs/reference/index.rst
src/conditions/__init__.py
src/conditions/exceptions.py
src/conditions/handlers.py
src/conditions/restarts.py
src/conditions/signals.py
src/conditions.egg-info/PKG-INFO
src/conditions.egg-info/SOURCES.txt
src/conditions.egg-info/dependency_links.txt
src/conditions.egg-info/not-zip-safe
src/conditions.egg-info/top_level.txt
tests/test_conditions.py